ettayi/__init__.py
ettayi/__main__.py
ettayi/cli.py
ettayi/interpreter.py
ettayi/parser.py
ettayi-1.0.6.dist-info/LICENSE
ettayi-1.0.6.dist-info/METADATA
ettayi-1.0.6.dist-info/WHEEL
ettayi-1.0.6.dist-info/entry_points.txt
ettayi-1.0.6.dist-info/top_level.txt
ettayi-1.0.6.dist-info/RECORD
