Metadata-Version: 2.1
Name: ettayi
Version: 1.0.6
Summary: Ettayi Lang
Home-page: https://github.com/Apollo-Blaze/ettayi
Author: Apollo-Blaze
Author-email: srichandsureshrocks@gmail.com
Classifier: Programming Language :: Python
Classifier: License :: OSI Approved :: MIT License
Classifier: Operating System :: OS Independent
Requires-Python: >=3.6
License-File: LICENSE
Requires-Dist: lark-parser >=0.12.0
